setup.py
cobertura2clover/__init__.py
cobertura2clover/parser.py
cobertura2clover.egg-info/PKG-INFO
cobertura2clover.egg-info/SOURCES.txt
cobertura2clover.egg-info/dependency_links.txt
cobertura2clover.egg-info/entry_points.txt
cobertura2clover.egg-info/not-zip-safe
cobertura2clover.egg-info/requires.txt
cobertura2clover.egg-info/top_level.txt